{
	"$schema": "http://schema.management.azure.com/schemas/2015-01-01/deploymentTemplate.json#",
	"contentVersion": "1.0.0.0",
	"parameters": {
		"factoryName": {
			"type": "string",
			"metadata": "Data Factory name",
			"defaultValue": "ADF-Waheed"
		}
	},
	"variables": {
		"factoryId": "[concat('Microsoft.DataFactory/factories/', parameters('factoryName'))]"
	},
	"resources": [
		{
			"name": "[concat(parameters('factoryName'), '/SqlServerTable2')]",
			"type": "Microsoft.DataFactory/factories/datasets",
			"apiVersion": "2018-06-01",
			"properties": {
				"linkedServiceName": {
					"referenceName": "poc_colzanilive_onprem",
					"type": "LinkedServiceReference"
				},
				"parameters": {
					"src_tbl": {
						"type": "string"
					}
				},
				"annotations": [],
				"type": "SqlServerTable",
				"schema": [],
				"typeProperties": {
					"schema": "dbo",
					"table": {
						"value": "@dataset().src_tbl",
						"type": "Expression"
					}
				}
			},
			"dependsOn": []
		},
		{
			"name": "[concat(parameters('factoryName'), '/onprem_to_Stg')]",
			"type": "Microsoft.DataFactory/factories/pipelines",
			"apiVersion": "2018-06-01",
			"properties": {
				"activities": [
					{
						"name": "Itrate_foreach_table",
						"type": "ForEach",
						"dependsOn": [
							{
								"activity": "select_scheema",
								"dependencyConditions": [
									"Succeeded"
								]
							}
						],
						"userProperties": [],
						"typeProperties": {
							"items": {
								"value": "@activity('select_scheema').output.value",
								"type": "Expression"
							},
							"activities": [
								{
									"name": "Copy_data",
									"type": "Copy",
									"dependsOn": [],
									"policy": {
										"timeout": "7.00:00:00",
										"retry": 0,
										"retryIntervalInSeconds": 30,
										"secureOutput": false,
										"secureInput": false
									},
									"userProperties": [],
									"typeProperties": {
										"source": {
											"type": "SqlServerSource",
											"additionalColumns": [
												{
													"name": "Ins_Date",
													"value": {
														"value": "@utcnow()",
														"type": "Expression"
													}
												},
												{
													"name": "upd_Date",
													"value": "NULL"
												}
											],
											"queryTimeout": "02:00:00",
											"partitionOption": "None"
										},
										"sink": {
											"type": "AzureSqlSink",
											"preCopyScript": {
												"value": "@{concat('truncate table ',item().name)}",
												"type": "Expression"
											},
											"writeBehavior": "insert",
											"sqlWriterUseTableLock": false,
											"tableOption": "autoCreate",
											"disableMetricsCollection": false
										},
										"enableStaging": false,
										"translator": {
											"type": "TabularTranslator",
											"typeConversion": true,
											"typeConversionSettings": {
												"allowDataTruncation": true,
												"treatBooleanAsNumber": false
											}
										}
									},
									"inputs": [
										{
											"referenceName": "SqlServerTable2",
											"type": "DatasetReference",
											"parameters": {
												"src_tbl": {
													"value": "@item().name",
													"type": "Expression"
												}
											}
										}
									],
									"outputs": [
										{
											"referenceName": "AzureSqlTable1",
											"type": "DatasetReference",
											"parameters": {
												"des_tbl": {
													"value": "@concat(item().name,'_test')",
													"type": "Expression"
												}
											}
										}
									]
								}
							]
						}
					},
					{
						"name": "select_scheema",
						"type": "Lookup",
						"dependsOn": [],
						"policy": {
							"timeout": "7.00:00:00",
							"retry": 0,
							"retryIntervalInSeconds": 30,
							"secureOutput": false,
							"secureInput": false
						},
						"userProperties": [],
						"typeProperties": {
							"source": {
								"type": "SqlServerSource",
								"sqlReaderQuery": "select name from sys.tables where name in ('parts','purchase_order')",
								"queryTimeout": "02:00:00",
								"partitionOption": "None"
							},
							"dataset": {
								"referenceName": "SqlServerTable1",
								"type": "DatasetReference",
								"parameters": {}
							},
							"firstRowOnly": false
						}
					},
					{
						"name": "Round hour",
						"type": "Script",
						"dependsOn": [],
						"policy": {
							"timeout": "7.00:00:00",
							"retry": 0,
							"retryIntervalInSeconds": 30,
							"secureOutput": false,
							"secureInput": false
						},
						"userProperties": [],
						"linkedServiceName": {
							"referenceName": "LS_des_POC",
							"type": "LinkedServiceReference"
						},
						"typeProperties": {
							"scripts": [
								{
									"type": "Query",
									"text": "select * \nfrom [dbo].[CurrencyRate]\nORDER BY [Date] DESC"
								}
							]
						}
					}
				],
				"policy": {
					"elapsedTimeMetric": {},
					"cancelAfter": {}
				},
				"annotations": [],
				"lastPublishTime": "2022-06-23T13:20:18Z"
			},
			"dependsOn": [
				"[concat(variables('factoryId'), '/datasets/SqlServerTable2')]"
			]
		},
		{
			"name": "[concat(parameters('factoryName'), '/Currency conversion Tri Hourly')]",
			"type": "Microsoft.DataFactory/factories/triggers",
			"apiVersion": "2018-06-01",
			"properties": {
				"annotations": [],
				"runtimeState": "Started",
				"pipelines": [
					{
						"pipelineReference": {
							"referenceName": "Load USD to PKR Currency Conversion Hourly Data",
							"type": "PipelineReference"
						},
						"parameters": {}
					}
				],
				"type": "ScheduleTrigger",
				"typeProperties": {
					"recurrence": {
						"frequency": "Minute",
						"interval": 2,
						"startTime": "2022-09-15T11:49:00",
						"timeZone": "Pakistan Standard Time"
					}
				}
			},
			"dependsOn": []
		}
	]
}